ics_sync.py
ics_to_org-1.0.3.dist-info/METADATA
ics_to_org-1.0.3.dist-info/WHEEL
ics_to_org-1.0.3.dist-info/entry_points.txt
ics_to_org-1.0.3.dist-info/licenses/LICENSE
ics_to_org-1.0.3.dist-info/RECORD
