Metadata-Version: 2.4
Name: ics-to-org
Version: 1.0.3
Summary: Sync iCalendar events to org-mode files while preserving your notes
Project-URL: Homepage, https://github.com/andyreagan/ics-to-org
Project-URL: Repository, https://github.com/andyreagan/ics-to-org
Project-URL: Issues, https://github.com/andyreagan/ics-to-org/issues
Author-email: Andy Reagan <andy@andyreagan.com>
License: MIT License
License-File: LICENSE
Classifier: License :: OSI Approved :: MIT License
Classifier: Operating System :: OS Independent
Classifier: Programming Language :: Python :: 3
Classifier: Programming Language :: Python :: 3.10
Classifier: Programming Language :: Python :: 3.11
Classifier: Programming Language :: Python :: 3.12
Classifier: Topic :: Office/Business :: Scheduling
Classifier: Topic :: Text Editors :: Emacs
Requires-Python: >=3.10
Requires-Dist: icalendar>=5.0.0
Provides-Extra: dev
Requires-Dist: black>=23.0.0; extra == 'dev'
Requires-Dist: mypy>=1.0.0; extra == 'dev'
Requires-Dist: pre-commit>=3.0.0; extra == 'dev'
Requires-Dist: pytest-cov>=4.0.0; extra == 'dev'
Requires-Dist: pytest>=7.0.0; extra == 'dev'
Requires-Dist: ruff>=0.1.0; extra == 'dev'
